Metadata-Version: 2.1
Name: coeur
Version: 1.1.0
Summary: Coeur service framework
Home-page: https://github.com/reritom/coeur
Author: Tomas Sheers
Author-email: t.sheers@outlook.com
License: MIT
Project-URL: Issues, https://github.com/reritom/coeur/issues
Keywords: coeur-services
Platform: UNKNOWN
Classifier: Development Status :: 4 - Beta
Classifier: Environment :: Web Environment
Classifier: Intended Audience :: Developers
Classifier: License :: OSI Approved :: MIT License
Classifier: Natural Language :: English
Classifier: Programming Language :: Python :: 3
Classifier: Programming Language :: Python :: 3.8
Classifier: Topic :: Internet :: WWW/HTTP :: Dynamic Content
Requires-Python: >=3.8
